studentit
