Metadata-Version: 1.0
Name: studentit-bookit-client
Version: 0.2.2
Summary: API client and command line application for connecting to BookIT
Home-page: https://github.com/cmbrad/studentit-bookit-client
Author: Christopher Bradley
Author-email: chris.bradley@unimelb.edu.au
License: UNKNOWN
Platform: UNKNOWN
